<?xml version="1.0" encoding="utf-8"?>
<FDRFile version="0.12" type="save">
  <SaveInfo>
    <Title>New Game</Title>
    <Timestamp>23.3.2009 21:03:06</Timestamp>
    <EngineVersion>0.25.2775</EngineVersion>
    <ModVersion>0.01</ModVersion>
    <CurrentYear>3100</CurrentYear>
    <CurrentCycle>1</CurrentCycle>
  </SaveInfo>
  <CustomComponents>
    <StationManager>
      <Stations>
        <Station type="Teraluwide.DeuterosEx.DeuterosGame.Stations.Station" title="Earth City" location="MilkyWay.Sol.Earth" owner="Player">
          <Modules>
            <MiningStore>
              <StoreItems>
                <Derrick>10</Derrick>
              </StoreItems>
              <StoreMaterials />
            </MiningStore>
            <MiningFacility derricks="5" />
          </Modules>
        </Station>
      </Stations>
    </StationManager>
  </CustomComponents>  
  <ResearchedItems>
    <Iron />
    <Titanium />
    <Aluminium />
    <Carbon />
    <Copper />
    <Hydrogen />
    <Deuterium />
    <Methane />
    <Helium />
    <Paladium />
    <Platinum />
    <Silver />
    <Gold />
    <Silica />
    <Derrick />
    <ShuttleChassis />
    <ShuttleDrive />
    <MeHFuel />
    <OFFrame />
    <SupplyPod />
    <ToolPod />
    <CryoPod />
    <Blaser />
    <IOSChassis />
    <IOSDrive />
    <SCGChassis />
    <SCGDrive />
    <HeDFuel />
    <ACC />
    <AOC />
    <Bandaid />
    <SDM />
    <Grapple />
    <DFCC />
    <AMA />
    <Hyperlight />
    <MTX />
    <FuzLaser />
    <RFrame />
    <PTL />
    <CommsPod />
    <IOSDrone />
    <StarDrone />
    <PrisonPod />
    <Blaster />
  </ResearchedItems>
  <ResearchItems />
</FDRFile>